google/cloud/vmwareengine/__init__.py
google/cloud/vmwareengine/gapic_version.py
google/cloud/vmwareengine/py.typed
google/cloud/vmwareengine_v1/__init__.py
google/cloud/vmwareengine_v1/gapic_metadata.json
google/cloud/vmwareengine_v1/gapic_version.py
google/cloud/vmwareengine_v1/py.typed
google/cloud/vmwareengine_v1/services/__init__.py
google/cloud/vmwareengine_v1/services/vmware_engine/__init__.py
google/cloud/vmwareengine_v1/services/vmware_engine/async_client.py
google/cloud/vmwareengine_v1/services/vmware_engine/client.py
google/cloud/vmwareengine_v1/services/vmware_engine/pagers.py
google/cloud/vmwareengine_v1/services/vmware_engine/transports/__init__.py
google/cloud/vmwareengine_v1/services/vmware_engine/transports/base.py
google/cloud/vmwareengine_v1/services/vmware_engine/transports/grpc.py
google/cloud/vmwareengine_v1/services/vmware_engine/transports/grpc_asyncio.py
google/cloud/vmwareengine_v1/services/vmware_engine/transports/rest.py
google/cloud/vmwareengine_v1/services/vmware_engine/transports/rest_base.py
google/cloud/vmwareengine_v1/types/__init__.py
google/cloud/vmwareengine_v1/types/vmwareengine.py
google/cloud/vmwareengine_v1/types/vmwareengine_resources.py
google_cloud_vmwareengine-1.10.0.dist-info/licenses/LICENSE
google_cloud_vmwareengine-1.10.0.dist-info/METADATA
google_cloud_vmwareengine-1.10.0.dist-info/WHEEL
google_cloud_vmwareengine-1.10.0.dist-info/top_level.txt
google_cloud_vmwareengine-1.10.0.dist-info/RECORD
