Metadata-Version: 2.4
Name: google-cloud-vmwareengine
Version: 1.10.0
Summary: Google Cloud Vmwareengine API client library
Home-page: https://github.com/googleapis/google-cloud-python/tree/main/packages/google-cloud-vmwareengine
Author: Google LLC
Author-email: googleapis-packages@google.com
License: Apache 2.0
Platform: Posix; MacOS X; Windows
Classifier: Development Status :: 5 - Production/Stable
Classifier: Intended Audience :: Developers
Classifier: License :: OSI Approved :: Apache Software License
Classifier: Programming Language :: Python
Classifier: Programming Language :: Python :: 3
Classifier: Programming Language :: Python :: 3.7
Classifier: Programming Language :: Python :: 3.8
Classifier: Programming Language :: Python :: 3.9
Classifier: Programming Language :: Python :: 3.10
Classifier: Programming Language :: Python :: 3.11
Classifier: Programming Language :: Python :: 3.12
Classifier: Programming Language :: Python :: 3.13
Classifier: Programming Language :: Python :: 3.14
Classifier: Operating System :: OS Independent
Classifier: Topic :: Internet
Requires-Python: >=3.7
License-File: LICENSE
Requires-Dist: google-api-core[grpc]!=2.0.*,!=2.1.*,!=2.10.*,!=2.2.*,!=2.3.*,!=2.4.*,!=2.5.*,!=2.6.*,!=2.7.*,!=2.8.*,!=2.9.*,<3.0.0,>=1.34.1
Requires-Dist: google-auth!=2.24.0,!=2.25.0,<3.0.0,>=2.14.1
Requires-Dist: grpcio<2.0.0,>=1.33.2
Requires-Dist: grpcio<2.0.0,>=1.75.1; python_version >= "3.14"
Requires-Dist: proto-plus<2.0.0,>=1.22.3
Requires-Dist: proto-plus<2.0.0,>=1.25.0; python_version >= "3.13"
Requires-Dist: protobuf!=4.21.0,!=4.21.1,!=4.21.2,!=4.21.3,!=4.21.4,!=4.21.5,<7.0.0,>=3.20.2
Requires-Dist: grpc-google-iam-v1<1.0.0,>=0.14.0
Dynamic: author
Dynamic: author-email
Dynamic: classifier
Dynamic: description
Dynamic: home-page
Dynamic: license
Dynamic: license-file
Dynamic: platform
Dynamic: requires-dist
Dynamic: requires-python
Dynamic: summary
